Csnr.cpython-37m-darwin.so
PhenomD.cpython-37m-darwin.so
gwsnrcalc/__init__.py
gwsnrcalc/generate_contour_data.py
gwsnrcalc/gw_snr_calculator.py
gwsnrcalc/genconutils/__init__.py
gwsnrcalc/genconutils/forminput.py
gwsnrcalc/genconutils/genprocess.py
gwsnrcalc/genconutils/readout.py
gwsnrcalc/utils/Csnr.c
gwsnrcalc/utils/PhenomD.c
gwsnrcalc/utils/__init__.py
gwsnrcalc/utils/csnr.py
gwsnrcalc/utils/parallel.py
gwsnrcalc/utils/readnoisecurves.py
gwsnrcalc/utils/sensitivity.py
gwsnrcalc/utils/waveforms.py
gwsnrcalc/utils/noise_curves/CL.txt
gwsnrcalc/utils/noise_curves/CLLF.txt
gwsnrcalc/utils/noise_curves/HB_wd_noise.txt
gwsnrcalc/utils/noise_curves/LPA.txt
gwsnrcalc/utils/noise_curves/PL.txt
gwsnrcalc/utils/noise_curves/PLCS.txt
gwsnrcalc/utils/noise_curves/PLHB.txt
gwsnrcalc/utils/src/phenomd.c
gwsnrcalc/utils/src/phenomd.h
gwsnrcalc/utils/src/ringdown_spectrum_fitting.h
gwsnrcalc/utils/src/snr.c
gwsnrcalc-1.1.0.dist-info/LICENSE
gwsnrcalc-1.1.0.dist-info/METADATA
gwsnrcalc-1.1.0.dist-info/WHEEL
gwsnrcalc-1.1.0.dist-info/top_level.txt
gwsnrcalc-1.1.0.dist-info/RECORD
