Metadata-Version: 2.1
Name: gwsnrcalc
Version: 1.1.0
Summary: Gravitational waveforms and snr.
Home-page: https://github.com/mikekatz04/BOWIE/snr_calculator_folder
Author: Michael Katz
Author-email: mikekatz04@gmail.com
License: UNKNOWN
Platform: UNKNOWN
Classifier: Programming Language :: Python :: 3
Classifier: Operating System :: OS Independent
Requires-Dist: numpy
Requires-Dist: scipy
Requires-Dist: astropy
Requires-Dist: h5py
